filePile.py
file_pile-1.0.0.dist-info/METADATA
file_pile-1.0.0.dist-info/WHEEL
file_pile-1.0.0.dist-info/top_level.txt
file_pile-1.0.0.dist-info/RECORD
