Metadata-Version: 2.1
Name: file-pile
Version: 1.0.0
Summary: To operate large numbers of files in a easy way.
Home-page: https://glowmem.com
Author: AiCorein
Author-email: melodyecho@glowmem.com
License: UNKNOWN
Platform: UNKNOWN
